Compiled from "HelloWorldApp.java"
class HelloWorldApp {
  HelloWorldApp();
    Code:
       0: aload_0
       1: invokespecial #1                  // Method java/lang/Object."<init>":()V
       4: return
    LineNumberTable:
      line 1: 0

  public static void main(java.lang.String[]);
    Code:
       0: invokestatic  #2                  // Method HelloWorldPerformer.perform:()V
       3: return
    LineNumberTable:
      line 3: 0
      line 4: 3
}
Compiled from "HelloWorldPerformer.java"
public class HelloWorldPerformer {
  public HelloWorldPerformer();
    Code:
       0: aload_0
       1: invokespecial #1                  // Method java/lang/Object."<init>":()V
       4: return
    LineNumberTable:
      line 1: 0

  public static void perform();
    Code:
       0: getstatic     #2                  // Field java/lang/System.out:Ljava/io/PrintStream;
       3: ldc           #3                  // String Hello World!
       5: invokevirtual #4                  // Method java/io/PrintStream.println:(Ljava/lang/String;)V
       8: return
    LineNumberTable:
      line 3: 0
      line 4: 8
}
