Compiled from "HelloWorldPerformer.java"
public class hello.world.HelloWorldPerformer$StaticInner {
  public hello.world.HelloWorldPerformer$StaticInner();
    Code:
       0: aload_0
       1: invokespecial #1                  // Method java/lang/Object."<init>":()V
       4: return
    LineNumberTable:
      line 4: 0

  public static void perform();
    Code:
       0: getstatic     #2                  // Field java/lang/System.out:Ljava/io/PrintStream;
       3: ldc           #3                  // String Hello World! (static)
       5: invokevirtual #4                  // Method java/io/PrintStream.println:(Ljava/lang/String;)V
       8: return
    LineNumberTable:
      line 6: 0
      line 7: 8
}
Compiled from "HelloWorldPerformer.java"
public class hello.world.HelloWorldPerformer$Inner {
  final hello.world.HelloWorldPerformer this$0;

  public hello.world.HelloWorldPerformer$Inner(hello.world.HelloWorldPerformer);
    Code:
       0: aload_0
       1: aload_1
       2: putfield      #1                  // Field this$0:Lhello/world/HelloWorldPerformer;
       5: aload_0
       6: invokespecial #2                  // Method java/lang/Object."<init>":()V
       9: return
    LineNumberTable:
      line 9: 0

  public void perform();
    Code:
       0: getstatic     #3                  // Field java/lang/System.out:Ljava/io/PrintStream;
       3: ldc           #4                  // String Hello World! (inner)
       5: invokevirtual #5                  // Method java/io/PrintStream.println:(Ljava/lang/String;)V
       8: return
    LineNumberTable:
      line 11: 0
      line 12: 8
}
Compiled from "HelloWorldPerformer.java"
public class hello.world.HelloWorldPerformer {
  public hello.world.HelloWorldPerformer();
    Code:
       0: aload_0
       1: invokespecial #1                  // Method java/lang/Object."<init>":()V
       4: return
    LineNumberTable:
      line 3: 0

  public void perform();
    Code:
       0: new           #2                  // class hello/world/HelloWorldPerformer$Inner
       3: dup
       4: aload_0
       5: invokespecial #3                  // Method hello/world/HelloWorldPerformer$Inner."<init>":(Lhello/world/HelloWorldPerformer;)V
       8: astore_1
       9: aload_1
      10: invokevirtual #4                  // Method hello/world/HelloWorldPerformer$Inner.perform:()V
      13: return
    LineNumberTable:
      line 15: 0
      line 16: 9
      line 17: 13
}
Compiled from "HelloWorldApp.java"
class HelloWorldApp {
  HelloWorldApp();
    Code:
       0: aload_0
       1: invokespecial #1                  // Method java/lang/Object."<init>":()V
       4: return
    LineNumberTable:
      line 3: 0

  public static void main(java.lang.String[]);
    Code:
       0: invokestatic  #2                  // Method hello/world/HelloWorldPerformer$StaticInner.perform:()V
       3: new           #3                  // class hello/world/HelloWorldPerformer
       6: dup
       7: invokespecial #4                  // Method hello/world/HelloWorldPerformer."<init>":()V
      10: invokevirtual #5                  // Method hello/world/HelloWorldPerformer.perform:()V
      13: return
    LineNumberTable:
      line 5: 0
      line 6: 3
      line 7: 13
}
